[
    {
        "Collaborator":"Abdoulbaki Djibo",
        "Gender":"male",
        "Affiliation":"Abdou Moumouni University",
        "Country":"Niger",
        "Coordinate location":"13.50136111,2.09852778",
        "URL":"https:\/\/remoboko.hypotheses.org\/tag\/abdoulbaki-djibo"
    },
    {
        "Collaborator":"Adedeji Adebayo",
        "Gender":"male",
        "Affiliation":"University of Ibadan",
        "Country":"Nigeria",
        "Coordinate location":"7.4416666666667,3.9",
        "URL":"https:\/\/remoboko.hypotheses.org\/tag\/adebayo-adedeji"
    },
    {
        "Collaborator":"Adeyemi Balogun",
        "Gender":"male",
        "Affiliation":"Osun State University",
        "Country":"Nigeria",
        "Coordinate location":"7.7616469,4.6012166",
        "URL":"https:\/\/remoboko.hypotheses.org\/tag\/adeyemi-balogun"
    },
    {
        "Collaborator":"Agn\u00e8s Badou",
        "Gender":"female",
        "Affiliation":"Laboratoire d'Etudes et de Recherche sur les Dynamiques Sociales et le D\u00e9veloppement Local B\u00e9nin",
        "Country":"Benin",
        "Coordinate location":"9.341822504659815,2.592843961135946",
        "URL":"https:\/\/remoboko.hypotheses.org\/tag\/agnes-badou"
    },
    {
        "Collaborator":"Ahmadou Hamage Issa",
        "Gender":"male",
        "Affiliation":"University of Bayreuth",
        "Country":"Germany",
        "Coordinate location":"49.92885,11.5859",
        "URL":"https:\/\/remoboko.hypotheses.org\/tag\/ahmadou-hamage-issa"
    },
    {
        "Collaborator":"Amadou Issoufou",
        "Gender":"male",
        "Affiliation":"Abdou Moumouni University",
        "Country":"Niger",
        "Coordinate location":"13.50136111,2.09852778",
        "URL":"https:\/\/remoboko.hypotheses.org\/tag\/amadou-issoufou"
    },
    {
        "Collaborator":"Amadou Oumarou",
        "Gender":"male",
        "Affiliation":"Abdou Moumouni University",
        "Country":"Niger",
        "Coordinate location":"13.50136111,2.09852778",
        "URL":"https:\/\/remoboko.hypotheses.org\/tag\/amadou-oumarou"
    },
    {
        "Collaborator":"Amanda tho Seeth",
        "Gender":"female",
        "Affiliation":"German Institute for Global and Area Studies",
        "Country":"Germany",
        "Coordinate location":"53.557222,9.992222",
        "URL":"https:\/\/remoboko.hypotheses.org\/tag\/amanda-tho-seeth"
    },
    {
        "Collaborator":"Anandita Bajpai",
        "Gender":"female",
        "Affiliation":"Leibniz-Zentrum Moderner Orient",
        "Country":"Germany",
        "Coordinate location":"52.427976,13.202396",
        "URL":"https:\/\/remoboko.hypotheses.org\/tag\/anandita-bajpai"
    },
    {
        "Collaborator":"Andr\u00e9 Chappatte",
        "Gender":"male",
        "Affiliation":"University of Geneva",
        "Country":"Switzerland",
        "Coordinate location":"46.19899, 6.14446",
        "URL":"https:\/\/remoboko.hypotheses.org\/tag\/andre-chappatte"
    },
    {
        "Collaborator":"Anna Schenkenberger",
        "Gender":"female",
        "Affiliation":"Leibniz-Zentrum Moderner Orient",
        "Country":"Germany",
        "Coordinate location":"52.427976,13.202396",
        "URL":"https:\/\/remoboko.hypotheses.org\/tag\/anna-schenkenberger"
    },
    {
        "Collaborator":"Anna Schnieder-Kr\u00fcger",
        "Gender":"female",
        "Affiliation":"Humboldt University of Berlin",
        "Country":"Germany",
        "Coordinate location":"52.518055555556,13.393333333333",
        "URL":"https:\/\/remoboko.hypotheses.org\/tag\/anna-schnieder-kruger"
    },
    {
        "Collaborator":"Anne Heffernan",
        "Gender":"female",
        "Affiliation":"Durham University",
        "Country":"United Kingdom",
        "Coordinate location":"54.775,-1.575",
        "URL":"https:\/\/remoboko.hypotheses.org\/tag\/anne-heffernan"
    },
    {
        "Collaborator":"Benjamin Lawrance",
        "Gender":"male",
        "Affiliation":"University of Arizona",
        "Country":"United States of America",
        "Coordinate location":"32.231667, -110.951944",
        "URL":"https:\/\/remoboko.hypotheses.org\/tag\/benjamin-lawrance"
    },
    {
        "Collaborator":"Benedikt Pontzen",
        "Gender":"male",
        "Affiliation":"Leibniz-Zentrum Moderner Orient",
        "Country":"Germany",
        "Coordinate location":"52.427976,13.202396",
        "URL":"https:\/\/remoboko.hypotheses.org\/tag\/benedikt-pontzen"
    },
    {
        "Collaborator":"Birgit Meyer",
        "Gender":"female",
        "Affiliation":"Utrecht University",
        "Country":"Netherlands",
        "Coordinate location":"52.085277777777776,5.175",
        "URL":"https:\/\/remoboko.hypotheses.org\/tag\/birgit-meyer"
    },
    {
        "Collaborator":"Britta Bayer",
        "Gender":"female",
        "Affiliation":"University of Cologne",
        "Country":"Germany",
        "Coordinate location":"50.928055555556,6.9286111111111",
        "URL":"https:\/\/remoboko.hypotheses.org\/tag\/britta-bayer"
    },
    {
        "Collaborator":"Bruno Reinhardt",
        "Gender":"male",
        "Affiliation":"Universidade Federal de Santa Catarina",
        "Country":"Brazil",
        "Coordinate location":"-27.6011,-48.52",
        "URL":"https:\/\/remoboko.hypotheses.org\/tag\/bruno-reinhardt"
    },
    {
        "Collaborator":"Chikas Ishaku Tsilpi",
        "Gender":"female",
        "Affiliation":"University of Jos",
        "Country":"Nigeria",
        "Coordinate location":"9.9692,8.884",
        "URL":"https:\/\/remoboko.hypotheses.org\/tag\/chikas-ishaku-tsilpi"
    },
    {
        "Collaborator":"Cindy Morillas",
        "Gender":"female",
        "Affiliation":"University of Johannesburg",
        "Country":"South Africa",
        "Coordinate location":"-26.183333333333,27.998888888889",
        "URL":"https:\/\/remoboko.hypotheses.org\/tag\/cindy-morillas"
    },
    {
        "Collaborator":"Daniele Cantini",
        "Gender":"male",
        "Affiliation":"University of Halle-Wittenberg",
        "Country":"Germany",
        "Coordinate location":"51.48638889,11.96888889",
        "URL":"https:\/\/remoboko.hypotheses.org\/tag\/daniele-cantini"
    },
    {
        "Collaborator":"Danladi Abah",
        "Gender":"male",
        "Affiliation":"Kogi State University",
        "Country":"Nigeria",
        "Coordinate location":"7.480942,7.187462",
        "URL":"https:\/\/remoboko.hypotheses.org\/tag\/danladi-abah"
    },
    {
        "Collaborator":"Dorothea Schulz",
        "Gender":"female",
        "Affiliation":"University of M\u00fcnster",
        "Country":"Germany",
        "Coordinate location":"51.964,7.613",
        "URL":"https:\/\/remoboko.hypotheses.org\/tag\/dorothea-schulz"
    },
    {
        "Collaborator":"Dr. Afdawaiza",
        "Gender":"male",
        "Affiliation":"Sunan Kalijaga Islamic University",
        "Country":"Indonesia",
        "Coordinate location":"-7.784758110931052,110.39435184060227",
        "URL":"https:\/\/remoboko.hypotheses.org\/tag\/dr-afdawaiza"
    },
    {
        "Collaborator":"Duane Jethro",
        "Gender":"male",
        "Affiliation":"Centre for Anthropological Research on Museums and Heritage",
        "Country":"Germany",
        "Coordinate location":"52.51272058842476,13.395041557671924",
        "URL":"https:\/\/remoboko.hypotheses.org\/tag\/duane-jethro"
    },
    {
        "Collaborator":"Ebenezer Obadare",
        "Gender":"male",
        "Affiliation":"Council on Foreign Relations",
        "Country":"United States of America",
        "Coordinate location":"40.768496836563955, -73.96615065791954",
        "URL":"https:\/\/remoboko.hypotheses.org\/tag\/ebenezer-obadare"
    },
    {
        "Collaborator":"\u00c9lodie Apard",
        "Gender":"female",
        "Affiliation":"Les Afriques dans le monde",
        "Country":"France",
        "Coordinate location":"44.806666666666665,-0.6311111111111111",
        "URL":"https:\/\/remoboko.hypotheses.org\/tag\/elodie-apard"
    },
    {
        "Collaborator":"Eva Spies",
        "Gender":"female",
        "Affiliation":"University of Bayreuth",
        "Country":"Germany",
        "Coordinate location":"49.92885,11.5859",
        "URL":"https:\/\/remoboko.hypotheses.org\/tag\/eva-spies"
    },
    {
        "Collaborator":"Francis Ars\u00e8ne Fogu\u00e9 Kuat\u00e9",
        "Gender":"male",
        "Affiliation":"Universit\u00e9 de Bu\u00e9a",
        "Country":"Cameroon",
        "Coordinate location":"4.14977,9.28774",
        "URL":"https:\/\/remoboko.hypotheses.org\/tag\/francis-arsene-fogue-kuate"
    },
    {
        "Collaborator":"Gado Alzouma",
        "Gender":"male",
        "Affiliation":"Abdou Moumouni University",
        "Country":"Niger",
        "Coordinate location":"13.50136111,2.09852778",
        "URL":"https:\/\/remoboko.hypotheses.org\/tag\/gado-alzouma"
    },
    {
        "Collaborator":"Gerd Spittler",
        "Gender":"male",
        "Affiliation":"University of Bayreuth",
        "Country":"Germany",
        "Coordinate location":"49.92885,11.5859",
        "URL":"https:\/\/remoboko.hypotheses.org\/tag\/gerd-spittler"
    },
    {
        "Collaborator":"Guy Bucumi",
        "Gender":"male",
        "Affiliation":"University of Sherbrooke",
        "Country":"Canada",
        "Coordinate location":"45.379405555556,-71.927661111111",
        "URL":"https:\/\/remoboko.hypotheses.org\/tag\/guy-bucumi"
    },
    {
        "Collaborator":"Hamani Oumarou",
        "Gender":"male",
        "Affiliation":"Abdou Moumouni University",
        "Country":"Niger",
        "Coordinate location":"13.50136111,2.09852778",
        "URL":"https:\/\/remoboko.hypotheses.org\/tag\/hamani-oumarou"
    },
    {
        "Collaborator":"Hamissou Rhissa Achaffert",
        "Gender":"male",
        "Affiliation":"University of Bayreuth",
        "Country":"Germany",
        "Coordinate location":"49.92885,11.5859",
        "URL":"https:\/\/remoboko.hypotheses.org\/tag\/hamissou-rhissa-achaffert"
    },
    {
        "Collaborator":"Hassan Mwakimako",
        "Gender":"male",
        "Affiliation":"Pwani University",
        "Country":"Kenya",
        "Coordinate location":"-3.620714, 39.844392",
        "URL":"https:\/\/remoboko.hypotheses.org\/tag\/hassan-mwakimako"
    },
    {
        "Collaborator":"Ibrahim Bachir Abdoulaye",
        "Gender":"male",
        "Affiliation":"University of Bayreuth",
        "Country":"Germany",
        "Coordinate location":"49.92885,11.5859",
        "URL":"https:\/\/remoboko.hypotheses.org\/tag\/ibrahim-bachir-abdoulaye"
    },
    {
        "Collaborator":"Ibrahim Moussa",
        "Gender":"male",
        "Affiliation":"Andr\u00e9 Salifou University of Zinder",
        "Country":"Niger",
        "Coordinate location":"13.84311,8.98637",
        "URL":"https:\/\/remoboko.hypotheses.org\/tag\/ibrahim-moussa"
    },
    {
        "Collaborator":"Inayah Rohmaniyah",
        "Gender":"female",
        "Affiliation":"Sunan Kalijaga Islamic University",
        "Country":"Indonesia",
        "Coordinate location":"-7.784758110931052,110.39435184060227",
        "URL":"https:\/\/remoboko.hypotheses.org\/tag\/inayah-rohmaniyah"
    },
    {
        "Collaborator":"Issouf Binat\u00e9",
        "Gender":"male",
        "Affiliation":"Universit\u00e9 Alassane Ouattara",
        "Country":"Ivory Coast",
        "Coordinate location":"7.68642,-5.06669",
        "URL":"https:\/\/remoboko.hypotheses.org\/tag\/issouf-binate"
    },
    {
        "Collaborator":"Jana Kleibert",
        "Gender":"female",
        "Affiliation":"Leibniz Institute for Research on Society and Space",
        "Country":"Germany",
        "Coordinate location":"52.4276,13.7561",
        "URL":"https:\/\/remoboko.hypotheses.org\/tag\/jana-kleibert"
    },
    {
        "Collaborator":"Jean-Pierre Olivier de Sardan",
        "Gender":"male",
        "Affiliation":"Laboratoire d'Etudes et de Recherche sur les Dynamiques Sociales et le D\u00e9veloppement Local",
        "Country":"Niger",
        "Coordinate location":"13.548915,2.096388",
        "URL":"https:\/\/remoboko.hypotheses.org\/tag\/jean-pierre-olivier-de-sardan"
    },
    {
        "Collaborator":"John Schmalzbauer",
        "Gender":"male",
        "Affiliation":"Missouri State University",
        "Country":"United States of America",
        "Coordinate location":"37.19971,-93.28079",
        "URL":"https:\/\/remoboko.hypotheses.org\/tag\/john-schmalzbauer"
    },
    {
        "Collaborator":"Judith Scheele",
        "Gender":"female",
        "Affiliation":"Leibniz-Zentrum Moderner Orient",
        "Country":"Germany",
        "Coordinate location":"52.427976,13.202396",
        "URL":"https:\/\/remoboko.hypotheses.org\/tag\/judith-scheele"
    },
    {
        "Collaborator":"June Temitope Gbadamosi",
        "Gender":"female",
        "Affiliation":"University of Ibadan",
        "Country":"Nigeria",
        "Coordinate location":"7.4416666666667,3.9",
        "URL":"https:\/\/remoboko.hypotheses.org\/tag\/june-temitope-gbadamosi"
    },
    {
        "Collaborator":"Kae Amo",
        "Gender":"female",
        "Affiliation":"School for Advanced Studies in the Social Sciences",
        "Country":"France",
        "Coordinate location":"48.83607,2.37205",
        "URL":"https:\/\/remoboko.hypotheses.org\/tag\/kae-amo"
    },
    {
        "Collaborator":"Kai Kresse",
        "Gender":"male",
        "Affiliation":"Leibniz-Zentrum Moderner Orient",
        "Country":"Germany",
        "Coordinate location":"52.427976,13.202396",
        "URL":"https:\/\/remoboko.hypotheses.org\/tag\/kai-kresse"
    },
    {
        "Collaborator":"Karen Lauterbach",
        "Gender":"female",
        "Affiliation":"University of Copenhagen",
        "Country":"Denmark",
        "Coordinate location":"55.679722222222,12.5725",
        "URL":"https:\/\/remoboko.hypotheses.org\/tag\/karen-lauterbach"
    },
    {
        "Collaborator":"Kasim Mohammed Ameen",
        "Gender":"male",
        "Affiliation":"Islamic University College, Ghana",
        "Country":"Ghana",
        "Coordinate location":"5.655742895900232,-0.11712973230672785",
        "URL":"https:\/\/remoboko.hypotheses.org\/tag\/mohammed-ameen-kasim"
    },
    {
        "Collaborator":"Katrin Bromber",
        "Gender":"female",
        "Affiliation":"Leibniz-Zentrum Moderner Orient",
        "Country":"Germany",
        "Coordinate location":"52.427976,13.202396",
        "URL":"https:\/\/remoboko.hypotheses.org\/tag\/katrin-bromber"
    },
    {
        "Collaborator":"Katrina Daly Thompson",
        "Gender":"female",
        "Affiliation":"University of Wisconsin–Madison",
        "Country":"United States of America",
        "Coordinate location":"43.075278, -89.409722",
        "URL":"https:\/\/remoboko.hypotheses.org\/tag\/katrina-daly-thompson"
    },
    {
        "Collaborator":"Koudbi Kabor\u00e9",
        "Gender":"male",
        "Affiliation":"University Joseph Ki-Zerbo",
        "Country":"Burkina Faso",
        "Coordinate location":"12.37722,-1.50083",
        "URL":"https:\/\/remoboko.hypotheses.org\/tag\/koudbi-kabore"
    },
    {
        "Collaborator":"Lassane Ouedraogo",
        "Gender":"male",
        "Affiliation":"Ohio University",
        "Country":"United States of America",
        "Coordinate location":"39.3275,-82.1",
        "URL":"https:\/\/remoboko.hypotheses.org\/tag\/lassane-ouedraogo"
    },
    {
        "Collaborator":"Laure Assaf",
        "Gender":"female",
        "Affiliation":"New York University Abu Dhabi",
        "Country":"United Arab Emirates",
        "Coordinate location":"24.5239,54.4346",
        "URL":"https:\/\/remoboko.hypotheses.org\/tag\/laure-assaf"
    },
    {
        "Collaborator":"Leonardo A. Villalón",
        "Gender":"male",
        "Affiliation":"University of Florida",
        "Country":"United States of America",
        "Coordinate location":"29.6475, -82.345",
        "URL":"https:\/\/remoboko.hypotheses.org\/tag\/leonardo-a-villalon"
    },
    {
        "Collaborator":"Lucie Revilla",
        "Gender":"female",
        "Affiliation":"Les Afriques dans le monde",
        "Country":"France",
        "Coordinate location":"44.806666666666665,-0.6311111111111111",
        "URL":"https:\/\/remoboko.hypotheses.org\/tag\/lucie-revilla"
    },
    {
        "Collaborator":"Mahamadou Bello Adamou",
        "Gender":"male",
        "Affiliation":"Abdou Moumouni University",
        "Country":"Niger",
        "Coordinate location":"13.50136111,2.09852778",
        "URL":"https:\/\/remoboko.hypotheses.org\/tag\/mahamadou-bello-adamou"
    },
    {
        "Collaborator":"Malam Sani Mahaboubou",
        "Gender":"male",
        "Affiliation":"Abdou Moumouni University",
        "Country":"Niger",
        "Coordinate location":"13.50136111,2.09852778",
        "URL":"https:\/\/remoboko.hypotheses.org\/tag\/malam-sani-mahaboubou"
    },
    {
        "Collaborator":"Mamadou Y\u00e9ro Bald\u00e9",
        "Gender":"male",
        "Affiliation":"Universit\u00e9 Cheikh Anta Diop",
        "Country":"Senegal",
        "Coordinate location":"14.686955,-17.463338",
        "URL":"https:\/\/remoboko.hypotheses.org\/tag\/mamadou-yero-balde"
    },
    {
        "Collaborator":"Manja Stephan-Emmrich",
        "Gender":"female",
        "Affiliation":"Humboldt University of Berlin",
        "Country":"Germany",
        "Coordinate location":"52.518055555556,13.393333333333",
        "URL":"https:\/\/remoboko.hypotheses.org\/tag\/manja-stephan-emmrich"
    },
    {
        "Collaborator":"Mara A. Leichtman",
        "Gender":"female",
        "Affiliation":"Michigan State University",
        "Country":"United States of America",
        "Coordinate location":"42.7018637482531,-84.48216117291386",
        "URL":"https:\/\/remoboko.hypotheses.org\/tag\/mara-a-leichtman"
    },
    {
        "Collaborator":"Marius Kothor",
        "Gender":"female",
        "Affiliation":"Harvard University",
        "Country":"United States of America",
        "Coordinate location":"42.374444, -71.116944",
        "URL":"https:\/\/remoboko.hypotheses.org\/tag\/marius-kothor"
    },
    {
        "Collaborator":"Mbaye Lo",
        "Gender":"male",
        "Affiliation":"Duke University",
        "Country":"United States of America",
        "Coordinate location":"36.001111111111,-78.938888888889",
        "URL":"https:\/\/remoboko.hypotheses.org\/tag\/mbaye-lo"
    },
    {
        "Collaborator":"Mounkaila Abdou",
        "Gender":"male",
        "Affiliation":"Abdou Moumouni University",
        "Country":"Niger",
        "Coordinate location":"13.50136111,2.09852778",
        "URL":"https:\/\/remoboko.hypotheses.org\/tag\/mounkaila-abdou"
    },
    {
        "Collaborator":"Muhammad Wildan",
        "Gender":"male",
        "Affiliation":"Sunan Kalijaga Islamic University",
        "Country":"Indonesia",
        "Coordinate location":"-7.784758110931052,110.39435184060227",
        "URL":"https:\/\/remoboko.hypotheses.org\/tag\/muhammad-wildan"
    },
    {
        "Collaborator":"Muhammad Yakasai",
        "Gender":"male",
        "Affiliation":"Humboldt University of Berlin",
        "Country":"Germany",
        "Coordinate location":"52.518055555556,13.393333333333",
        "URL":"https:\/\/remoboko.hypotheses.org\/tag\/muhammad-yakasai"
    },
    {
        "Collaborator":"Murtala Ibrahim",
        "Gender":"male",
        "Affiliation":"Free University Berlin",
        "Country":"Germany",
        "Coordinate location":"52.453055555556,13.290555555556",
        "URL":"https:\/\/remoboko.hypotheses.org\/tag\/murtala-ibrahim"
    },
    {
        "Collaborator":"Mutiat Titilope Oladejo",
        "Gender":"female",
        "Affiliation":"University of Ibadan",
        "Country":"Nigeria",
        "Coordinate location":"7.4416666666667,3.9",
        "URL":"https:\/\/remoboko.hypotheses.org\/tag\/mutiat-titilope-oladejo"
    },
    {
        "Collaborator":"Nadir A. Nasidi",
        "Gender":"male",
        "Affiliation":"Ahmadu Bello University",
        "Country":"Nigeria",
        "Coordinate location":"11.15,7.65",
        "URL":"https:\/\/remoboko.hypotheses.org\/tag\/nadir-a-nasidi"
    },
    {
        "Collaborator":"Najoum Alhassane",
        "Gender":"male",
        "Affiliation":"University of Bayreuth",
        "Country":"Germany",
        "Coordinate location":"49.92885,11.5859",
        "URL":"https:\/\/remoboko.hypotheses.org\/tag\/najoum-alhassane"
    },
    {
        "Collaborator":"Olubunmi Olowookere",
        "Gender":"female",
        "Affiliation":"University of Ibadan",
        "Country":"Nigeria",
        "Coordinate location":"7.4416666666667,3.9",
        "URL":"https:\/\/remoboko.hypotheses.org\/tag\/olubunmi-olowookere"
    },
    {
        "Collaborator":"Olutayo Adesina",
        "Gender":"male",
        "Affiliation":"University of Ibadan",
        "Country":"Nigeria",
        "Coordinate location":"7.4416666666667,3.9",
        "URL":"https:\/\/remoboko.hypotheses.org\/tag\/olutayo-adesina"
    },
    {
        "Collaborator":"Oumarou Moussa",
        "Gender":"male",
        "Affiliation":"Abdou Moumouni University",
        "Country":"Niger",
        "Coordinate location":"13.50136111,2.09852778",
        "URL":"https:\/\/remoboko.hypotheses.org\/tag\/oumarou-moussa"
    },
    {
        "Collaborator":"Ousmanou Adama",
        "Gender":"male",
        "Affiliation":"Universit\u00e9 de Maroua",
        "Country":"Cameroon",
        "Coordinate location":"10.35,14.19",
        "URL":"https:\/\/remoboko.hypotheses.org\/tag\/ousmanou-adama"
    },
    {
        "Collaborator":"Paul Stoller",
        "Gender":"male",
        "Affiliation":"West Chester University of Pennsylvania",
        "Country":"United States of America",
        "Coordinate location":"39.9522, -75.6001",
        "URL":"https:\/\/remoboko.hypotheses.org\/tag\/paul-stoller"
    },
    {
        "Collaborator":"Pedro Monaville",
        "Gender":"male",
        "Affiliation":"New York University Abu Dhabi",
        "Country":"United Arab Emirates",
        "Coordinate location":"24.5239,54.4346",
        "URL":"https:\/\/remoboko.hypotheses.org\/tag\/pedro-monaville"
    },
    {
        "Collaborator":"Rebecca Babirye",
        "Gender":"female",
        "Affiliation":"Tokyo Christian University",
        "Country":"Japan",
        "Coordinate location":"35.7379,139.827",
        "URL":"https:\/\/remoboko.hypotheses.org\/tag\/rebecca-babirye"
    },
    {
        "Collaborator":"Robby Habiba Abror",
        "Gender":"male",
        "Affiliation":"Sunan Kalijaga Islamic University",
        "Country":"Indonesia",
        "Coordinate location":"-7.784758110931052,110.39435184060227",
        "URL":"https:\/\/remoboko.hypotheses.org\/tag\/robby-habiba-abror"
    },
    {
        "Collaborator":"Robert Launay",
        "Gender":"male",
        "Affiliation":"Northwestern University",
        "Country":"United States of America",
        "Coordinate location":"42.054853,-87.673945",
        "URL":"https:\/\/remoboko.hypotheses.org\/tag\/robert-launay"
    },
    {
        "Collaborator":"Sadia Bajwa",
        "Gender":"female",
        "Affiliation":"Humboldt University of Berlin",
        "Country":"Germany",
        "Coordinate location":"52.518055555556,13.393333333333",
        "URL":"https:\/\/remoboko.hypotheses.org\/tag\/sadia-bajwa"
    },
    {
        "Collaborator":"Sadia Mahmood",
        "Gender":"female",
        "Affiliation":"Quaid-i-Azam University",
        "Country":"Pakistan",
        "Coordinate location":"33.75,73.13333333",
        "URL":"https:\/\/remoboko.hypotheses.org\/tag\/sadia-mahmood"
    },
    {
        "Collaborator":"Sana Chavoshian",
        "Gender":"female",
        "Affiliation":"Leibniz-Zentrum Moderner Orient",
        "Country":"Germany",
        "Coordinate location":"52.427976,13.202396",
        "URL":"https:\/\/remoboko.hypotheses.org\/tag\/sana-chavoshian"
    },
    {
        "Collaborator":"Sekou Sala Timbely",
        "Gender":"male",
        "Affiliation":"S\u00e9gou University",
        "Country":"Mali",
        "Coordinate location":"13.42465383620792,-6.303292125339687",
        "URL":"https:\/\/remoboko.hypotheses.org\/tag\/sekou-sala-timbely"
    },
    {
        "Collaborator":"Seyni Mamoudou Ibrahim",
        "Gender":"male",
        "Affiliation":"University of Bayreuth",
        "Country":"Germany",
        "Coordinate location":"49.92885,11.5859",
        "URL":"https:\/\/remoboko.hypotheses.org\/tag\/seyni-mamoudou-ibrahim"
    },
    {
        "Collaborator":"Shofiyullah Muzammil",
        "Gender":"male",
        "Affiliation":"Sunan Kalijaga Islamic University",
        "Country":"Indonesia",
        "Coordinate location":"-7.784758110931052,110.39435184060227",
        "URL":"https:\/\/remoboko.hypotheses.org\/tag\/shofiyullah-muzammil"
    },
    {
        "Collaborator":"Simbarashe Gukurume",
        "Gender":"male",
        "Affiliation":"Sol Plaatje University",
        "Country":"South Africa",
        "Coordinate location":"-28.74511818,24.76427601",
        "URL":"https:\/\/remoboko.hypotheses.org\/tag\/simbarashe-gukurume"
    },
    {
        "Collaborator":"Stefan Kirmse",
        "Gender":"male",
        "Affiliation":"Leibniz-Zentrum Moderner Orient",
        "Country":"Germany",
        "Coordinate location":"52.427976,13.202396",
        "URL":"https:\/\/remoboko.hypotheses.org\/tag\/stefan-kirmse"
    },
    {
        "Collaborator":"Stephen T. Ogundipe",
        "Gender":"male",
        "Affiliation":"Obafemi Awolowo University",
        "Country":"Nigeria",
        "Coordinate location":"7.51833333,4.52277778",
        "URL":"https:\/\/remoboko.hypotheses.org\/tag\/stephen-t-ogundipe"
    },
    {
        "Collaborator":"Tatiana Smirnova",
        "Gender":"female",
        "Affiliation":"Universit\u00e9 du Qu\u00e9bec \u00e0 Montr\u00e9al",
        "Country":"Canada",
        "Coordinate location":"45.513888888889,-73.560277777778",
        "URL":"https:\/\/remoboko.hypotheses.org\/tag\/tatiana-smirnova"
    },
    {
        "Collaborator":"Thomas Veret",
        "Gender":"male",
        "Affiliation":"Sorbonne Nouvelle-Paris 3",
        "Country":"France",
        "Coordinate location":"48.84488888888889,2.396988888888889",
        "URL":"https:\/\/remoboko.hypotheses.org\/tag\/thomas-veret"
    },
    {
        "Collaborator":"Ulrike Freitag",
        "Gender":"female",
        "Affiliation":"Leibniz-Zentrum Moderner Orient",
        "Country":"Germany",
        "Coordinate location":"52.427976,13.202396",
        "URL":"https:\/\/remoboko.hypotheses.org\/tag\/ulrike-freitag"
    },
    {
        "Collaborator":"Yekatit Getachew Tsehayu",
        "Gender":"female",
        "Affiliation":"University of Florida",
        "Country":"United States of America",
        "Coordinate location":"29.6475,-82.345",
        "URL":"https:\/\/remoboko.hypotheses.org\/tag\/yekatit-getachew-tsehayu"
    },
    {
        "Collaborator":"Youssoufou Bakayoko",
        "Gender":"male",
        "Affiliation":"Universit\u00e9 Alassane Ouattara",
        "Country":"Ivory Coast",
        "Coordinate location":"7.68642,-5.06669",
        "URL":"https:\/\/remoboko.hypotheses.org\/tag\/youssoufou-bakayoko"
    },
    {
        "Collaborator":"Yunus Dumbe",
        "Gender":"male",
        "Affiliation":"Kwame Nkrumah University of Science and Technology",
        "Country":"Ghana",
        "Coordinate location":"6.684903,-1.570514",
        "URL":"https:\/\/remoboko.hypotheses.org\/tag\/yunus-dumbe"
    }
]